MANIFEST.in
README.md
UNLICENSE
pyproject.toml
readme.md
setup.py
tvdb_api.py
tests/test_tvdb_api.py
tvdb_api.egg-info/PKG-INFO
tvdb_api.egg-info/SOURCES.txt
tvdb_api.egg-info/dependency_links.txt
tvdb_api.egg-info/requires.txt
tvdb_api.egg-info/top_level.txt